src/defines.vh
//=========================================
//             MEMORY PARAMETERS
//=========================================
`define IMEM_SIZE 1024  // Para instruções tipo-R
`define DMEM_SIZE 1024  // Para instruções tipo-R

//=========================================
//             ALUOp CODES (2 bits)
//=========================================
`define ALUOP_RTYPE         2'b10  // Para instruções tipo-R
`define ALUOP_BEQ_BNE       2'b01  // Para beq e bne (SUB)
`define ALUOP_LW_SW_ADDI    2'b00  // Para lw, sw e addi (ADD)
`define ALUOP_ANDI_ORI_XORI 2'b11  // Para instruções ANDI, ORI, XORI

//=========================================
// ULA INTERNAL CODES - ARBITRARY (4 bits)
//=========================================
`define ALU_ADD   4'b0001 // R.1
`define ALU_SUB   4'b0010 // R.2

`define ALU_AND   4'b0011 // R.3
`define ALU_OR    4'b0100 // R.4
`define ALU_XOR   4'b0101 // R.5
`define ALU_NOR   4'b0110 // R.6

`define ALU_SLT   4'b0111 // R.7
`define ALU_SLTU  4'b1000 // R.8
`define ALU_SLL   4'b1001 // R.9
`define ALU_SRL   4'b1010 // R.10
`define ALU_SRA   4'b1011 // R.11

`define ALU_SLLV  4'b1100 // R.12
`define ALU_SRLV  4'b1101 // R.13
`define ALU_SRAV  4'b1110 // R.14

`define ALU_JR    4'b1111 // R.15

//=========================================
//        FUNCT FOR R-TYPE (6 bits)
//=========================================
`define FUNCT_ADD   6'b100000 // R.1 
`define FUNCT_SUB   6'b100010 // R.2 

`define FUNCT_AND   6'b100100 // R.3 
`define FUNCT_OR    6'b100101 // R.4 
`define FUNCT_XOR   6'b100110 // R.5 
`define FUNCT_NOR   6'b100111 // R.6 

`define FUNCT_SLT   6'b101010 // R.7
`define FUNCT_SLTU  6'b101011 // R.8 
`define FUNCT_SLL   6'b000000 // R.9 
`define FUNCT_SRL   6'b000010 // R.10 
`define FUNCT_SRA   6'b000011 // R.11 

`define FUNCT_SLLV  6'b000100 // R.12 
`define FUNCT_SRLV  6'b000110 // R.13 
`define FUNCT_SRAV  6'b000111 // R.14 

`define FUNCT_JR    6'b001000 // R.15 

//=========================================
//          MIPS OPCODES (6 bits)
//=========================================
`define MIPS_RTYPE  6'b000000  // Tipo R

`define MIPS_ADDI   6'b001000  // I.1
`define MIPS_ANDI   6'b001100  // I.2
`define MIPS_ORI    6'b001101  // I.3
`define MIPS_XORI   6'b001110  // I.4

`define MIPS_BEQ    6'b000100  // I.5
`define MIPS_BNE    6'b000101  // I.6
`define MIPS_SLTI   6'b001010  // I.7
`define MIPS_SLTIU  6'b001011  // I.8
`define MIPS_LUI    6'b001111  // I.9

`define MIPS_LW     6'b100011  // I.10
`define MIPS_SW     6'b101011  // I.11
//=========================================
`define MIPS_J      6'b000010  // J.1
`define MIPS_JAL    6'b000011  // J.2

src/control.v
`include "src/defines.vh"

module control(
  input [5:0] opcode,
  input [5:0] funct,     // Para detectar JR
  output reg RegDst,
  output reg Jump,
  output reg Branch,
  output reg MemRead,
  output reg MemtoReg,
  output reg [1:0] ALUOp,
  output reg MemWrite,
  output reg ALUSrc,
  output reg RegWrite,
  output reg Jr,           // Sinal para JR
  output reg ExtOp,        // Extensão de sinal
  output reg JalEn,        // Sinal para JAL
  output reg LuiEn         // Sinal para LUI
);
  always @(*) begin
    // Reset de todos os sinais
    RegDst   = 0;
    Jump     = 0;
    Branch   = 0;
    MemRead  = 0;
    MemtoReg = 0;
    ALUOp    = `ALUOP_LW_SW_ADDI;
    MemWrite = 0;
    ALUSrc   = 0;
    RegWrite = 0;
    Jr       = 0;
    ExtOp    = 1;
    JalEn    = 0;
    LuiEn    = 0;

    case (opcode)
      `MIPS_RTYPE: begin
        RegDst   = 1;
        RegWrite = 1;
        ALUOp    = `ALUOP_RTYPE;
        Jr       = (funct == `JR_FUNCT_CODE) ? 1 : 0;
      end

      `MIPS_LW: begin
        ALUSrc   = 1;
        MemtoReg = 1;
        RegWrite = 1;
        MemRead  = 1;
      end

      `MIPS_SW: begin
        ALUSrc   = 1;
        MemWrite = 1;
      end

      `MIPS_BEQ: begin
        Branch = 1;
        ALUOp  = `ALUOP_BEQ_BNE;
      end

      `MIPS_BNE: begin
        Branch = 1;
        ALUOp  = `ALUOP_BEQ_BNE;
      end

      `MIPS_ADDI: begin
        ALUSrc   = 1;
        RegWrite = 1;
      end

      `MIPS_ANDI: begin
        ALUSrc   = 1;
        RegWrite = 1;
        ExtOp    = 0;   // Extensão por zero
        ALUOp    = `ALUOP_ANDI_ORI_XORI;
      end

      `MIPS_ORI: begin
        ALUSrc   = 1;
        RegWrite = 1;
        ExtOp    = 0;   // Extensão por zero
        ALUOp    = `ALUOP_ANDI_ORI_XORI;
      end

      `MIPS_XORI: begin
        ALUSrc   = 1;
        RegWrite = 1;
        ExtOp    = 0;   // Extensão por zero
        ALUOp    = `ALUOP_ANDI_ORI_XORI;
      end

      `MIPS_J: begin
        Jump = 1;
      end

      `MIPS_JAL: begin
        Jump     = 1;
        RegWrite = 1;
        JalEn    = 1;
      end

      `MIPS_LUI: begin
        ALUSrc   = 1;
        RegWrite = 1;
        LuiEn    = 1;
      end

      default: begin
        // Instruções não implementadas
      end
    endcase
  end
endmodule

src/d_mem.v
//=========================================
//              DATA MEMORY
//=========================================
`include "src/defines.vh"

module d_mem(
  input clock,
  input MemRead,
  input MemWrite,
  input [31:0] address,
  input [31:0] WriteData,
  output [31:0] ReadData
);
  reg [31:0] mem [0:`IMEM_SIZE-1]; // Memória de 1K palavras
  
  assign ReadData = MemRead ? mem[address[11:2]] : 32'bz;
  
  always @(posedge clock) begin
    if (MemWrite)
      mem[address[11:2]] <= WriteData;
  end
endmodule

src/ula.v
//=========================================
//          ULA IMPLEMENTATION
//=========================================
`include "src/defines.vh"  // Inclui os defines com os códigos da ULA

module ula( 
  input [31:0] In1,        // Operando 1 (rs) 
  input [31:0] In2,        // Operando 2 (rt)
  input [4:0]  shamt,      // Quantidade de shift (novo)
  input [3:0]  OP,         // Código da operação (vem da ula_ctrl)
  output reg [31:0] result,
  output wire Zero_Flag
);
  always @(*) begin
    case (OP)
      `ALU_ADD:   result = In1 + In2;                                // R.1
      `ALU_SUB:   result = In1 - In2;                                // R.2
      `ALU_AND:   result = In1 & In2;                                // R.3
      `ALU_OR:    result = In1 | In2;                                // R.4
      `ALU_XOR:   result = In1 ^ In2;                                // R.5
      `ALU_NOR:   result = ~(In1 | In2);                             // R.6
      `ALU_SLT:   result = ($signed(In1) < $signed(In2)) ? 1 : 0;    // R.7
      `ALU_SLTU:  result = (In1 < In2) ? 1 : 0;                      // R.8
      `ALU_SLL:   result = In2 << shamt;                             // R.9
      `ALU_SRL:   result = In2 >> shamt;                             // R.10
      `ALU_SRA:   result = $signed(In2) >>> shamt;                   // R.11
      `ALU_SLLV:  result = In2 << In1[4:0];                          // R.12
      `ALU_SRLV:  result = In2 >> In1[4:0];                          // R.13
      `ALU_SRAV:  result = $signed(In2) >>> In1[4:0];                // R.14
      `ALU_JR:    result = In1;                                      // R.15
      default:    result = 0;
    endcase
  end

  assign Zero_Flag = (result == 0);
endmodule

src/ula_ctrl.v
//=========================================
//              ULA CONTROL
//=========================================
`include "src/defines.vh"

module ula_ctrl(
  input [1:0] ALUOp,
  input [5:0] funct,
  output reg [3:0] OP_ula
);
  always @(*) begin
    case (ALUOp)
      2'b00: OP_ula = `ALU_ADD;     // ADD (lw/sw/addi)
      2'b01: OP_ula = `ALU_SUB;     // SUB (beq/bne)
      2'b10: begin                  // Instruções tipo-R
        case (funct)
          `FUNCT_ADD:  OP_ula = `ALU_ADD;  // R.1
          `FUNCT_SUB:  OP_ula = `ALU_SUB;  // R.2
          `FUNCT_AND:  OP_ula = `ALU_AND;  // R.3
          `FUNCT_OR:   OP_ula = `ALU_OR;   // R.4
          `FUNCT_XOR:  OP_ula = `ALU_XOR;  // R.5
          `FUNCT_NOR:  OP_ula = `ALU_NOR;  // R.6
          `FUNCT_SLT:  OP_ula = `ALU_SLT;  // R.7
          `FUNCT_SLTU: OP_ula = `ALU_SLTU; // R.8
          `FUNCT_SLL:  OP_ula = `ALU_SLL;  // R.9
          `FUNCT_SRL:  OP_ula = `ALU_SRL;  // R.10
          `FUNCT_SRA:  OP_ula = `ALU_SRA;  // R.11
          `FUNCT_SLLV: OP_ula = `ALU_SLLV; // R.12
          `FUNCT_SRLV: OP_ula = `ALU_SRLV; // R.13
          `FUNCT_SRAV: OP_ula = `ALU_SRAV; // R.14
          `FUNCT_JR:   OP_ula = `ALU_JR;   // R.15
          default:     OP_ula = `ALU_ADD;
        endcase
      end
      default: OP_ula = `ALU_ADD;
    endcase
  end
endmodule

src/sign_extend.v
//=========================================
//              SIGN EXTEND
//=========================================
module sign_extend(
  input [15:0] imm,     // Imediato de 16 bits
  input ExtOp,          // 1= ext.signal, 0=ext.zero
  output reg [31:0] ext_out
);
  always @(*) begin
    if (ExtOp)
      ext_out = {{16{imm[15]}}, imm};  // estende sinal
    else
      ext_out = {16'b0, imm};          // estende zero
  end
endmodule

src/regfile.v
//=========================================
//            REGISTERS BANK
//=========================================
module regfile(
  input clock,
  input reset,
  input RegWrite,            // Habilita escrita
  input [4:0] ReadAddr1,     // Endereço rs (Register Source)
  input [4:0] ReadAddr2,     // Endereço rt (Register Target)
  input [4:0] WriteAddr,     // Endereço rd (Register Destination/Tipo R)
  input [31:0] WriteData,    // Dado a Escrever
  output [31:0] ReadData1,   // Valor de rs
  output [31:0] ReadData2    // Valor de rt             
);
  reg [31:0] registers [0:31];  // 32 Registradores

  // Leitura assíncrona
  assign ReadData1 = (ReadAddr1 == 0) ? 32'b0 : registers[ReadAddr1];
  assign ReadData2 = (ReadAddr2 == 0) ? 32'b0 : registers[ReadAddr2];

  // Escrita síncrona (reset assincrono)
  always @(posedge clock or posedge reset) begin
    if (reset) begin
      for (integer i = 0; i < 32; i++)
        registers[i] <= 0;                // Zera todos os registradores
    end
    else if (RegWrite && WriteAddr != 0) begin
      registers[WriteAddr] <= WriteData;  // Escreve em rd (exceto $zero)
    end
  end
endmodule

src/i_mem.v
module i_mem #(
  parameter MEM_SIZE = 1024
)(
  input  wire [31:0] address,   // instruction address
  output wire [31:0] i_out      // 32 bits instruction
);

  reg [31:0] mem [0:MEM_SIZE-1];
  initial begin
    $readmemb("sim/mem.list", mem); // load external file
  end
  
  assign i_out = mem[address[11:2]]; // address by bytes, but instructions uses 32 bits (4 bytes) 
endmodule

src/pc.v
//=========================================
//           PROGRAM COUNTER
//=========================================
module PC(
  input clock,          // Sinal de Clock
  input reset,          // Reset Assíncrono
  input [31:0] nextPC,  // Próximo Endereço
  output reg [31:0] PC  // Endereço Atual
);
  always @(posedge clock or posedge reset) begin
    if (reset)  PC <= 32'h00000000;      // Reset para 0
    else        PC <= nextPC;            // Atualiza na borda de Subida
  end
endmodule

src/mips.v
//=========================================
//            MIPS / TOP-LEVEL
//=========================================
/*[opcode] [ rs ] [ rt ] [ rd ] [shamt] [funct]
   31-26   25-21  20-16  15-11    10-6   5-0   */

module mips(
  input clock,
  input reset,
  output [31:0] PCOut,
  output [31:0] ALUResultOut,
  output [31:0] MemOut
);
  // Conexões principais
  wire [31:0] PC, nextPC, instruction;
  wire [31:0] read_data1, read_data2, write_data;
  wire [31:0] sign_ext_out, alu_in2, dmem_out;
  wire [4:0] shamt = instruction[10:6];
  wire [5:0] funct = instruction[5:0];
  
  // Sinais de controle expandidos
  wire RegDst, Jump, Branch, MemRead, MemtoReg, MemWrite, ALUSrc, RegWrite, Jr, ExtOp, JalEn, LuiEn;
  wire [1:0] ALUOp;
  
  // Instância dos módulos principais
  PC pc(clock, reset, nextPC, PC);
  assign PCOut = PC;  // Saída do PC para depuração
  
  i_mem imem(PC, instruction);
  
  // Lógica de seleção de registrador de escrita
  wire [4:0] write_reg = 
    JalEn ? 5'b11111 :                                  // JAL usa $ra (reg 31)
    (RegDst ? instruction[15:11] : instruction[20:16]); // Padrão
  
  // Banco de registradores
  regfile regs(
    .clock(clock),
    .reset(reset),
    .RegWrite(RegWrite),
    .ReadAddr1(instruction[25:21]),  // rs
    .ReadAddr2(instruction[20:16]),  // rt
    .WriteAddr(write_reg),
    .WriteData(write_data),
    .ReadData1(read_data1),
    .ReadData2(read_data2)
  );
  
  // Extensão de sinal
  sign_extend ext(
    .imm(instruction[15:0]),
    .ExtOp(ExtOp),
    .ext_out(sign_ext_out)
  );
  
  // Seleção de entrada da ULA
  assign alu_in2 = ALUSrc ? sign_ext_out : read_data2;
  
  // Controle da ULA
  wire [3:0] alu_control;
  ula_ctrl uctrl(
    .ALUOp(ALUOp),
    .funct(funct),
    .OP_ula(alu_control)
  );
  
  // Unidade Lógica-Aritmética
  wire zero_flag;
  ula alu(
    .shamt(shamt),
    .In1(read_data1),
    .In2(alu_in2),
    .OP(alu_control),
    .result(ALUResultOut),
    .Zero_Flag(zero_flag)
  );
  
  // Memória de dados
  d_mem dmem(
    .clock(clock),
    .address(ALUResultOut),
    .WriteData(read_data2),
    .ReadData(dmem_out),
    .MemWrite(MemWrite),
    .MemRead(MemRead)
  );
  assign MemOut = dmem_out;  // Saída de memória para depuração
  
  // Cálculos de PC
  wire [31:0] pc_plus4 = PC + 4;
  wire [31:0] branch_offset = {sign_ext_out[29:0], 2'b00};
  wire [31:0] branch_target = pc_plus4 + branch_offset;
  wire is_jr = !(|instruction[31:26]) && (instruction[5:0] == 6'b001000);  // JR (opcode=0, funct=8)
  
  // Lógica de branch
  wire branch_taken = Branch & 
                     ((instruction[31:26] == 6'b000100 & zero_flag) |  // BEQ zero
                      (instruction[31:26] == 6'b000101 & ~zero_flag)); // BNE não-zero
  
  // Seleção do próximo PC
  assign nextPC = 
    is_jr     ? read_data1 :                                  // JR prioridade máxima
    Jump      ? {pc_plus4[31:28], instruction[25:0], 2'b00} : // Jump/JAL
    branch_taken ? branch_target :                            // Branch
    pc_plus4;                                                 // Sequencial

  // Seleção de dados para escrita no registrador
  assign write_data = 
    JalEn ? pc_plus4 :                     // JAL: escreve PC+4
    LuiEn ? {instruction[15:0], 16'b0} :   // LUI: {imm, 0}
    MemtoReg ? dmem_out :                  // LW: dado da memória
    ALUResultOut;                          // Padrão: resultado ULA

  // Unidade de controle
  control ctrl(
    .opcode(instruction[31:26]),
    .RegDst(RegDst),
    .Jump(Jump),
    .Branch(Branch),
    .MemRead(MemRead),
    .MemtoReg(MemtoReg),
    .ALUOp(ALUOp),
    .MemWrite(MemWrite),
    .ALUSrc(ALUSrc),
    .RegWrite(RegWrite),
    .Jr(Jr),
    .ExtOp(ExtOp),
    .JalEn(JalEn),
    .LuiEn(LuiEn)
  );

endmodule

sim/test.v
`timescale 1ns/1ps

module test;
  reg clk;
  reg reset;
  
  wire [31:0] pc;       // debug output
  wire [31:0] instr;    // debug output
  always #5 clk = ~clk; // alternate clock for each 5ns
  
  mips dut (            // create mips with top-level
    .clock(clk),
    .reset(reset)
  );

  initial begin
    $dumpfile("sim/wav.vcd"); // waveform out
    $dumpvars(0, test);       // testbench name
    
    clk = 0;       // start signal
    reset = 1;     // start signal
    #10 reset = 0; // Reset in 10ns
    
    #10000;     // emulate for 1000ns
    $finish;    // and stop
  end

endmodule

sim/waves.vcd
$date
	Tue Jul 29 20:57:59 2025
$end
$version
	Icarus Verilog
$end
$timescale
	1ps
$end
$scope module test $end
$var reg 1 ! clk $end
$var reg 1 " reset $end
$scope module dut $end
$var wire 32 # MemOut [31:0] $end
$var wire 32 $ PCOut [31:0] $end
$var wire 1 % branch_taken $end
$var wire 1 ! clock $end
$var wire 1 & is_jr $end
$var wire 1 " reset $end
$var wire 1 ' zero_flag $end
$var wire 5 ( write_reg [4:0] $end
$var wire 32 ) write_data [31:0] $end
$var wire 32 * sign_ext_out [31:0] $end
$var wire 5 + shamt [4:0] $end
$var wire 32 , read_data2 [31:0] $end
$var wire 32 - read_data1 [31:0] $end
$var wire 32 . pc_plus4 [31:0] $end
$var wire 32 / nextPC [31:0] $end
$var wire 32 0 instruction [31:0] $end
$var wire 6 1 funct [5:0] $end
$var wire 32 2 dmem_out [31:0] $end
$var wire 32 3 branch_target [31:0] $end
$var wire 32 4 branch_offset [31:0] $end
$var wire 32 5 alu_in2 [31:0] $end
$var wire 4 6 alu_control [3:0] $end
$var wire 1 7 RegWrite $end
$var wire 1 8 RegDst $end
$var wire 32 9 PC [31:0] $end
$var wire 1 : MemtoReg $end
$var wire 1 ; MemWrite $end
$var wire 1 < MemRead $end
$var wire 1 = LuiEn $end
$var wire 1 > Jump $end
$var wire 1 ? Jr $end
$var wire 1 @ JalEn $end
$var wire 1 A ExtOp $end
$var wire 1 B Branch $end
$var wire 1 C ALUSrc $end
$var wire 32 D ALUResultOut [31:0] $end
$var wire 2 E ALUOp [1:0] $end
$scope module alu $end
$var wire 32 F In2 [31:0] $end
$var wire 5 G shamt [4:0] $end
$var wire 1 ' Zero_Flag $end
$var wire 4 H OP [3:0] $end
$var wire 32 I In1 [31:0] $end
$var reg 32 J result [31:0] $end
$upscope $end
$scope module ctrl $end
$var wire 6 K funct [5:0] $end
$var wire 6 L opcode [5:0] $end
$var reg 2 M ALUOp [1:0] $end
$var reg 1 C ALUSrc $end
$var reg 1 B Branch $end
$var reg 1 A ExtOp $end
$var reg 1 @ JalEn $end
$var reg 1 ? Jr $end
$var reg 1 > Jump $end
$var reg 1 = LuiEn $end
$var reg 1 < MemRead $end
$var reg 1 ; MemWrite $end
$var reg 1 : MemtoReg $end
$var reg 1 8 RegDst $end
$var reg 1 7 RegWrite $end
$upscope $end
$scope module dmem $end
$var wire 1 < MemRead $end
$var wire 1 ; MemWrite $end
$var wire 32 N address [31:0] $end
$var wire 1 ! clock $end
$var wire 32 O WriteData [31:0] $end
$var wire 32 P ReadData [31:0] $end
$upscope $end
$scope module ext $end
$var wire 1 A ExtOp $end
$var wire 16 Q imm [15:0] $end
$var reg 32 R ext_out [31:0] $end
$upscope $end
$scope module imem $end
$var wire 32 S i_out [31:0] $end
$var wire 32 T address [31:0] $end
$upscope $end
$scope module pc $end
$var wire 1 ! clock $end
$var wire 32 U nextPC [31:0] $end
$var wire 1 " reset $end
$var reg 32 V PC [31:0] $end
$upscope $end
$scope module regs $end
$var wire 5 W ReadAddr1 [4:0] $end
$var wire 5 X ReadAddr2 [4:0] $end
$var wire 1 7 RegWrite $end
$var wire 5 Y WriteAddr [4:0] $end
$var wire 32 Z WriteData [31:0] $end
$var wire 1 ! clock $end
$var wire 1 " reset $end
$var wire 32 [ ReadData2 [31:0] $end
$var wire 32 \ ReadData1 [31:0] $end
$scope begin $ivl_for_loop0 $end
$var integer 32 ] i [31:0] $end
$upscope $end
$upscope $end
$scope module uctrl $end
$var wire 2 ^ ALUOp [1:0] $end
$var wire 6 _ funct [5:0] $end
$var reg 4 ` OP_ula [3:0] $end
$upscope $end
$upscope $end
$upscope $end
$enddefinitions $end
#0
$dumpvars
b10 `
b1111 _
b0 ^
b100000 ]
b0 \
b0 [
b11110000000000000000 Z
b1 Y
b1 X
b0 W
b0 V
b100 U
b0 T
b111100000000010000000000001111 S
b1111 R
b1111 Q
bz P
b0 O
b1111 N
b0 M
b1111 L
bz K
b1111 J
b0 I
b10 H
b0 G
b1111 F
b0 E
b1111 D
1C
0B
1A
0@
0?
0>
1=
0<
0;
0:
b0 9
08
17
b10 6
b1111 5
b111100 4
b1000000 3
bz 2
b1111 1
b111100000000010000000000001111 0
b100 /
b100 .
b0 -
b0 ,
b0 +
b1111 *
b11110000000000000000 )
b1 (
0'
0&
0%
b0 $
bz #
1"
0!
$end
#5000
b100000 ]
1!
#10000
0!
0"
#15000
b11111010000000000000 )
b11111010000000000000 Z
b101000000000000000 4
b1010000000000000 5
b1010000000000000 F
b11111010000000000000 D
b11111010000000000000 J
b11111010000000000000 N
b11 E
b11 M
b11 ^
0A
0=
17
1C
b1010000000000000 *
b1010000000000000 R
b11110000000000000000 -
b11110000000000000000 I
b11110000000000000000 \
b1000 /
b1000 U
b1101 L
b1010000000000000 Q
b1 W
b0 1
b0 _
b110100001000011010000000000000 0
b110100001000011010000000000000 S
b11110000000000000000 ,
b11110000000000000000 O
b11110000000000000000 [
b101000000000001000 3
b1000 .
b100 $
b100 9
b100 T
b100 V
1!
#20000
0!
#25000
b11111010000000000000 )
b11111010000000000000 Z
b11001 (
b11001 Y
b11111111111111110010000010000000 4
b11111010000000000000 5
b11111010000000000000 F
x?
18
1A
17
0C
b10 E
b10 M
b10 ^
b11111111111111111100100000100000 *
b11111111111111111100100000100000 R
b1100 /
b1100 U
b11111010000000000000 D
b11111010000000000000 J
b11111010000000000000 N
b0 L
b1100100000100000 Q
b0 W
b100000 1
b100000 _
b0 -
b0 I
b0 \
b11111010000000000000 ,
b11111010000000000000 O
b11111010000000000000 [
b11100100000100000 0
b11100100000100000 S
b11111111111111110010000010001100 3
b1100 .
b1000 $
b1000 9
b1000 T
b1000 V
1!
#30000
0!
#35000
b11111010000000000001 )
b11111010000000000001 Z
b1 5
b1 F
b100 4
b11111010000000000001 D
b11111010000000000001 J
b11111010000000000001 N
b11001 (
b11001 Y
1C
0?
17
b0 E
b0 M
b0 ^
08
b1 *
b1 R
b11111010000000000000 -
b11111010000000000000 I
b11111010000000000000 \
b10000 /
b10000 U
b1000 L
b1 Q
b11001 X
b11001 W
b1 1
b1 _
b100011001110010000000000000001 0
b100011001110010000000000000001 S
b10100 3
b10000 .
b1100 $
b1100 9
b1100 T
b1100 V
1!
#40000
0!
#45000
b10100 )
b10100 Z
b1010000 4
b10100 5
b10100 F
b10000 (
b10000 Y
b10100 *
b10100 R
b10100 /
b10100 U
b10100 D
b10100 J
b10100 N
b10100 Q
b10000 X
b0 W
b10100 1
b10100 _
b0 -
b0 I
b0 \
b0 ,
b0 O
b0 [
b100000000100000000000000010100 0
b100000000100000000000000010100 S
b1100100 3
b10100 .
b10000 $
b10000 9
b10000 T
b10000 V
1!
#50000
0!
#55000
b1111 )
b1111 Z
b1111 D
b1111 J
b1111 N
b111100 4
b1111 5
b1111 F
b10001 (
b10001 Y
b1111 *
b1111 R
b11000 /
b11000 U
b1111 Q
b10001 X
b1111 1
b1111 _
b100000000100010000000000001111 0
b100000000100010000000000001111 S
b0 ,
b0 O
b0 [
b1010100 3
b11000 .
b10100 $
b10100 9
b10100 T
b10100 V
1!
#60000
0!
#65000
b100011 )
b100011 Z
b1000 (
b1000 Y
b10000000010000000 4
b100011 D
b100011 J
b100011 N
x?
b10 E
b10 M
b10 ^
18
17
0C
b100000000100000 *
b100000000100000 R
b10100 -
b10100 I
b10100 \
b11100 /
b11100 U
b0 L
b100000000100000 Q
b10000 W
b100000 1
b100000 _
b1111 ,
b1111 O
b1111 [
b10000100010100000000100000 0
b10000100010100000000100000 S
b10000000010011100 3
b11100 .
b11000 $
b11000 9
b11000 T
b11000 V
1!
#70000
0!
#75000
b101 )
b101 Z
b10010000010001000 4
b1001 (
b1001 Y
b101 D
b101 J
b101 N
b100100000100010 *
b100100000100010 R
b11 6
b11 H
b11 `
b100000 /
b100000 U
b100100000100010 Q
b100010 1
b100010 _
b10000100010100100000100010 0
b10000100010100100000100010 S
b10010000010101000 3
b100000 .
b11100 $
b11100 9
b11100 T
b11100 V
1!
#80000
0!
#85000
b101000 )
b101000 Z
b1010000 4
b10100 5
b10100 F
b1010 (
b1010 Y
b101000 D
b101000 J
b101000 N
1C
0?
17
b0 E
b0 M
b0 ^
08
b10100 *
b10100 R
b0 ,
b0 O
b0 [
b10 6
b10 H
b10 `
b100100 /
b100100 U
b1000 L
b10100 Q
b1010 X
b10100 1
b10100 _
b100010000010100000000000010100 0
b100010000010100000000000010100 S
b1110100 3
b100100 .
b100000 $
b100000 9
b100000 T
b100000 V
1!
#90000
0!
#95000
b100 )
b100 Z
b100 D
b100 J
b100 N
b100 6
b100 H
b100 `
b10110000010010000 4
b1111 5
b1111 F
b1011 (
b1011 Y
x?
b10 E
b10 M
b10 ^
18
17
0C
b101100000100100 *
b101100000100100 R
b101000 /
b101000 U
b0 L
b101100000100100 Q
b10001 X
b100100 1
b100100 _
b10000100010101100000100100 0
b10000100010101100000100100 S
b1111 ,
b1111 O
b1111 [
b10110000010111000 3
b101000 .
b100100 $
b100100 9
b100100 T
b100100 V
1!
#100000
0!
#105000
b11111 )
b11111 Z
b11000000010010100 4
b1100 (
b1100 Y
b11111 D
b11111 J
b11111 N
b110000000100101 *
b110000000100101 R
b1 6
b1 H
b1 `
b101100 /
b101100 U
b110000000100101 Q
b100101 1
b100101 _
b10000100010110000000100101 0
b10000100010110000000100101 S
b11000000011000000 3
b101100 .
b101000 $
b101000 9
b101000 T
b101000 V
1!
#110000
0!
#115000
b11011 )
b11011 Z
b11010000010011000 4
b1101 (
b1101 Y
b11011 D
b11011 J
b11011 N
b110100000100110 *
b110100000100110 R
b101 6
b101 H
b101 `
b110000 /
b110000 U
b110100000100110 Q
b100110 1
b100110 _
b10000100010110100000100110 0
b10000100010110100000100110 S
b11010000011001000 3
b110000 .
b101100 $
b101100 9
b101100 T
b101100 V
1!
#120000
0!
#125000
b11111111111111111111111111100000 )
b11111111111111111111111111100000 Z
b11100000010011100 4
b1110 (
b1110 Y
b11111111111111111111111111100000 D
b11111111111111111111111111100000 J
b11111111111111111111111111100000 N
b111000000100111 *
b111000000100111 R
b110 6
b110 H
b110 `
b110100 /
b110100 U
b111000000100111 Q
b100111 1
b100111 _
b10000100010111000000100111 0
b10000100010111000000100111 S
b11100000011010000 3
b110100 .
b110000 $
b110000 9
b110000 T
b110000 V
1!
#130000
0!
#135000
b11111010000000000010 )
b11111010000000000010 Z
b100 4
b1 5
b1 F
b11001 (
b11001 Y
b11111010000000000010 D
b11111010000000000010 J
b11111010000000000010 N
1C
0?
17
b0 E
b0 M
b0 ^
08
b1 *
b1 R
b11111010000000000001 ,
b11111010000000000001 O
b11111010000000000001 [
b11111010000000000001 -
b11111010000000000001 I
b11111010000000000001 \
b10 6
b10 H
b10 `
b111000 /
b111000 U
b1000 L
b1 Q
b11001 X
b11001 W
b1 1
b1 _
b100011001110010000000000000001 0
b100011001110010000000000000001 S
b111100 3
b111000 .
b110100 $
b110100 9
b110100 T
b110100 V
1!
#140000
0!
#145000
b101 )
b101 Z
b10100 4
b101 5
b101 F
b10000 (
b10000 Y
b101 *
b101 R
b111100 /
b111100 U
b101 D
b101 J
b101 N
b101 Q
b10000 X
b0 W
b101 1
b101 _
b0 -
b0 I
b0 \
b10100 ,
b10100 O
b10100 [
b100000000100000000000000000101 0
b100000000100000000000000000101 S
b1010000 3
b111100 .
b111000 $
b111000 9
b111000 T
b111000 V
1!
#150000
0!
#155000
b10100 )
b10100 Z
b10100 D
b10100 J
b10100 N
b1010000 4
b10100 5
b10100 F
b10001 (
b10001 Y
b10100 *
b10100 R
b1000000 /
b1000000 U
b10100 Q
b10001 X
b10100 1
b10100 _
b100000000100010000000000010100 0
b100000000100010000000000010100 S
b1111 ,
b1111 O
b1111 [
b10010000 3
b1000000 .
b111100 $
b111100 9
b111100 T
b111100 V
1!
#160000
0!
#165000
b1000 6
b1000 H
b1000 `
b11111111111111100000001000000000 4
b101 5
b101 F
b10000 (
b10000 Y
x?
b10 E
b10 M
b10 ^
18
17
0C
b11111111111111111000000010000000 *
b11111111111111111000000010000000 R
b1000100 /
b1000100 U
b0 L
b1000000010000000 Q
b10000 X
b0 1
b0 _
b10 +
b10 G
b101 ,
b101 O
b101 [
b100001000000010000000 0
b100001000000010000000 S
b11111111111111100000001001000100 3
b1000100 .
b1000000 $
b1000000 9
b1000000 T
b1000000 V
1!
#170000
0!
#175000
b0 )
b0 Z
1%
b11111111111111111111111111111000 4
b10001 (
b10001 Y
1B
0?
07
b1 E
b1 M
b1 ^
08
b11111111111111111111111111111110 *
b11111111111111111111111111111110 R
b10100 -
b10100 I
b10100 \
b11 6
b11 H
b11 `
b1000000 /
b1000000 U
1'
b0 D
b0 J
b0 N
b100 L
b1111111111111110 Q
b10001 X
b10000 W
b111110 1
b111110 _
b11111 +
b11111 G
b10100 5
b10100 F
b10010000100011111111111111110 0
b10010000100011111111111111110 S
b10100 ,
b10100 O
b10100 [
b1000000 3
b1001000 .
b1000100 $
b1000100 9
b1000100 T
b1000100 V
1!
#180000
0!
#185000
b1010000 )
b1010000 Z
b1000 6
b1000 H
b1000 `
0%
b11111111111111100000001000000000 4
0'
b1010000 D
b1010000 J
b1010000 N
b10000 (
b10000 Y
x?
17
18
b10 E
b10 M
b10 ^
0B
b11111111111111111000000010000000 *
b11111111111111111000000010000000 R
b0 -
b0 I
b0 \
b1000100 /
b1000100 U
b0 L
b1000000010000000 Q
b10000 X
b0 W
b0 1
b0 _
b10 +
b10 G
b100001000000010000000 0
b100001000000010000000 S
b11111111111111100000001001000100 3
b1000100 .
b1000000 $
b1000000 9
b1000000 T
b1000000 V
1!
#190000
0!
#195000
b111100 )
b111100 Z
0%
b11111111111111111111111111111000 4
b10001 (
b10001 Y
1B
0?
07
b1 E
b1 M
b1 ^
08
b11111111111111111111111111111110 *
b11111111111111111111111111111110 R
b1010000 -
b1010000 I
b1010000 \
b11 6
b11 H
b11 `
b1001000 /
b1001000 U
0'
b111100 D
b111100 J
b111100 N
b100 L
b1111111111111110 Q
b10001 X
b10000 W
b111110 1
b111110 _
b11111 +
b11111 G
b10100 5
b10100 F
b10010000100011111111111111110 0
b10010000100011111111111111110 S
b10100 ,
b10100 O
b10100 [
b1000000 3
b1001000 .
b1000100 $
b1000100 9
b1000100 T
b1000100 V
1!
#200000
0!
